llama_index/embeddings/yandexgpt/__init__.py
llama_index/embeddings/yandexgpt/base.py
llama_index/embeddings/yandexgpt/util.py
llama_index_embeddings_yandexgpt-0.4.1.dist-info/METADATA
llama_index_embeddings_yandexgpt-0.4.1.dist-info/WHEEL
llama_index_embeddings_yandexgpt-0.4.1.dist-info/licenses/LICENSE
llama_index_embeddings_yandexgpt-0.4.1.dist-info/RECORD
