Metadata-Version: 2.4
Name: llama-index-embeddings-yandexgpt
Version: 0.4.1
Summary: llama-index embeddings yandexgpt integration
Author-email: Kirill Kukharev <k.kuharev@uniyar.ac.ru>
License-Expression: MIT
License-File: LICENSE
Requires-Python: <4.0,>=3.9
Requires-Dist: llama-index-core<0.15,>=0.13.0
Requires-Dist: tenacity>=8.3.0
